pygls/__init__.py
pygls/capabilities.py
pygls/constants.py
pygls/exceptions.py
pygls/feature_manager.py
pygls/progress.py
pygls/protocol.py
pygls/py.typed
pygls/server.py
pygls/uris.py
pygls/workspace.py
pygls/lsp/__init__.py
pygls/lsp/methods.py
pygls/lsp/types/__init__.py
pygls/lsp/types/basic_structures.py
pygls/lsp/types/client.py
pygls/lsp/types/diagnostics.py
pygls/lsp/types/file_operations.py
pygls/lsp/types/general_messages.py
pygls/lsp/types/text_synchronization.py
pygls/lsp/types/window.py
pygls/lsp/types/workspace.py
pygls/lsp/types/language_features/__init__.py
pygls/lsp/types/language_features/call_hierarchy.py
pygls/lsp/types/language_features/code_action.py
pygls/lsp/types/language_features/code_lens.py
pygls/lsp/types/language_features/color_presentation.py
pygls/lsp/types/language_features/completion.py
pygls/lsp/types/language_features/declaration.py
pygls/lsp/types/language_features/definition.py
pygls/lsp/types/language_features/document_color.py
pygls/lsp/types/language_features/document_highlight.py
pygls/lsp/types/language_features/document_link.py
pygls/lsp/types/language_features/document_symbol.py
pygls/lsp/types/language_features/folding_range.py
pygls/lsp/types/language_features/formatting.py
pygls/lsp/types/language_features/hover.py
pygls/lsp/types/language_features/implementation.py
pygls/lsp/types/language_features/linked_editing_range.py
pygls/lsp/types/language_features/monikers.py
pygls/lsp/types/language_features/on_type_formatting.py
pygls/lsp/types/language_features/prepare_rename.py
pygls/lsp/types/language_features/range_formatting.py
pygls/lsp/types/language_features/references.py
pygls/lsp/types/language_features/rename.py
pygls/lsp/types/language_features/selection_range.py
pygls/lsp/types/language_features/semantic_tokens.py
pygls/lsp/types/language_features/signature_help.py
pygls/lsp/types/language_features/type_definition.py
pygls_tagls_custom-0.0.1.data/data/lib/site_packages/pygls/ThirdPartyNotices.txt
pygls_tagls_custom-0.0.1.dist-info/LICENSE.txt
pygls_tagls_custom-0.0.1.dist-info/METADATA
pygls_tagls_custom-0.0.1.dist-info/WHEEL
pygls_tagls_custom-0.0.1.dist-info/top_level.txt
pygls_tagls_custom-0.0.1.dist-info/RECORD
