Metadata-Version: 2.1
Name: pygls-tagls-custom
Version: 0.0.1
Summary: a pythonic generic language server (pronounced like "pie glass").
Home-page: https://github.com/daquexian/pygls/tree/master/
Author: Open Law Library
Author-email: info@openlawlib.org
License: Apache 2.0
Keywords: python,pythonic,generic,language,server,protocol
Platform: UNKNOWN
Classifier: Development Status :: 3 - Alpha
Classifier: Intended Audience :: Developers
Classifier: Intended Audience :: Information Technology
Classifier: Topic :: Software Development :: Libraries :: Python Modules
Classifier: License :: OSI Approved :: Apache Software License
Classifier: Operating System :: OS Independent
Classifier: Programming Language :: Python :: 3 :: Only
Classifier: Programming Language :: Python :: 3.6
Classifier: Programming Language :: Python :: 3.7
Classifier: Programming Language :: Python :: 3.8
Classifier: Programming Language :: Python :: 3.9
Requires-Dist: pydantic (<1.9,>=1.7)
Requires-Dist: typeguard (<3,>=2.10.0)
Provides-Extra: dev
Requires-Dist: bandit (==1.6.0) ; extra == 'dev'
Requires-Dist: flake8 (==3.7.7) ; extra == 'dev'
Requires-Dist: mypy (==0.812) ; extra == 'dev'
Provides-Extra: docs
Requires-Dist: sphinx (==2.0.1) ; extra == 'docs'
Requires-Dist: sphinx-rtd-theme (==0.4.3) ; extra == 'docs'
Provides-Extra: test
Requires-Dist: mock (==3.0.5) ; extra == 'test'
Requires-Dist: pytest (==4.5.0) ; extra == 'test'
Requires-Dist: pytest-asyncio (==0.10.0) ; extra == 'test'
Provides-Extra: ws
Requires-Dist: websockets (==9.*) ; extra == 'ws'
